{
  "295580076249055242": {
    "experience": 5123,
    "level": 10,
    "balance": 16800,
    "rank": 6
  },
  "261438412563677185": {
    "experience": 27669,
    "level": 32,
    "balance": 4400,
    "rank": 1
  },
  "870204861680082954": {
    "experience": 5874,
    "level": 10,
    "balance": 1400,
    "rank": 5
  },
  "307746371967123457": {
    "experience": 249,
    "level": 3,
    "balance": 300,
    "rank": 39
  },
  "259740865319141376": {
    "experience": 833,
    "level": 5,
    "balance": 500,
    "rank": 12
  },
  "321272314933018625": {
    "experience": 509,
    "level": 4,
    "balance": 400,
    "rank": 21
  },
  "381307743853740051": {
    "experience": 16511,
    "level": 21,
    "balance": 2900,
    "rank": 2
  },
  "401451980502990880": {
    "experience": 13228,
    "level": 18,
    "balance": 3200,
    "rank": 3
  },
  "824310379885887508": {
    "experience": 962,
    "level": 6,
    "balance": 600,
    "rank": 10
  },
  "643557581410926602": {
    "experience": 8137,
    "level": 13,
    "balance": 1700,
    "rank": 4
  },
  "934582382936326254": {
    "experience": 123,
    "level": 1,
    "balance": 100,
    "rank": 183
  },
  "421308871605485569": {
    "experience": 117,
    "level": 1,
    "balance": 100,
    "rank": 287
  },
  "594957574445596733": {
    "experience": 251,
    "level": 3,
    "balance": 300,
    "rank": 38
  },
  "292957554538053634": {
    "experience": 123,
    "level": 1,
    "balance": 100,
    "rank": 182
  },
  "431810002643189760": {
    "experience": 844,
    "level": 5,
    "balance": 500,
    "rank": 11
  },
  "839821472066174997": {
    "experience": 119,
    "level": 1,
    "balance": 100,
    "rank": 257
  },
  "513092423459799043": {
    "experience": 119,
    "level": 1,
    "balance": 100,
    "rank": 256
  },
  "935245992171806760": {
    "experience": 253,
    "level": 3,
    "balance": 300,
    "rank": 37
  },
  "505691822874558475": {
    "experience": 2484,
    "level": 8,
    "balance": 800,
    "rank": 8
  },
  "424977762822914061": {
    "experience": 124,
    "level": 1,
    "balance": 100,
    "rank": 160
  },
  "283618370476048384": {
    "experience": 279,
    "level": 3,
    "balance": 300,
    "rank": 33
  },
  "404837388393906176": {
    "experience": 807,
    "level": 5,
    "balance": 500,
    "rank": 13
  },
  "638546113829535744": {
    "experience": 119,
    "level": 1,
    "balance": 100,
    "rank": 255
  },
  "708667212470157312": {
    "experience": 163,
    "level": 2,
    "balance": 200,
    "rank": 67
  },
  "423526055308165130": {
    "experience": 139,
    "level": 1,
    "balance": 100,
    "rank": 102
  },
  "382233207875305472": {
    "experience": 513,
    "level": 4,
    "balance": 400,
    "rank": 20
  },
  "483337670496616460": {
    "experience": 143,
    "level": 1,
    "balance": 100,
    "rank": 87
  },
  "172402117032673280": {
    "experience": 118,
    "level": 1,
    "balance": 100,
    "rank": 270
  },
  "716201755733655622": {
    "experience": 123,
    "level": 1,
    "balance": 100,
    "rank": 181
  },
  "821729041769168926": {
    "experience": 122,
    "level": 1,
    "balance": 100,
    "rank": 205
  },
  "821728168326201384": {
    "experience": 123,
    "level": 1,
    "balance": 100,
    "rank": 180
  },
  "908561182011584582": {
    "experience": 120,
    "level": 1,
    "balance": 100,
    "rank": 239
  },
  "862471478791766036": {
    "experience": 142,
    "level": 1,
    "balance": 100,
    "rank": 89
  },
  "306388202371940353": {
    "experience": 205,
    "level": 2,
    "balance": 200,
    "rank": 47
  },
  "289849279600787457": {
    "experience": 765,
    "level": 5,
    "balance": 500,
    "rank": 14
  },
  "647452054201171988": {
    "experience": 541,
    "level": 4,
    "balance": 400,
    "rank": 19
  },
  "761678882880749590": {
    "experience": 119,
    "level": 1,
    "balance": 100,
    "rank": 254
  },
  "933162120030347285": {
    "experience": 115,
    "level": 1,
    "balance": 100,
    "rank": 316
  },
  "441704298871652362": {
    "experience": 116,
    "level": 1,
    "balance": 100,
    "rank": 302
  },
  "873639619470708746": {
    "experience": 116,
    "level": 1,
    "balance": 100,
    "rank": 301
  },
  "713170524456615936": {
    "experience": 123,
    "level": 1,
    "balance": 100,
    "rank": 179
  },
  "711515258732150795": {
    "experience": 117,
    "level": 1,
    "balance": 100,
    "rank": 286
  },
  "631260154150649897": {
    "experience": 100,
    "level": 1,
    "balance": 100,
    "rank": 321
  },
  "101434113310867456": {
    "experience": 121,
    "level": 1,
    "balance": 100,
    "rank": 223
  },
  "921741549530923028": {
    "experience": 123,
    "level": 1,
    "balance": 100,
    "rank": 178
  },
  "201910079354568704": {
    "experience": 119,
    "level": 1,
    "balance": 100,
    "rank": 253
  },
  "917452331983986748": {
    "experience": 123,
    "level": 1,
    "balance": 100,
    "rank": 177
  },
  "896918152364032040": {
    "experience": 118,
    "level": 1,
    "balance": 100,
    "rank": 269
  },
  "266951980981682176": {
    "experience": 117,
    "level": 1,
    "balance": 100,
    "rank": 285
  },
  "297651949422247937": {
    "experience": 139,
    "level": 1,
    "balance": 100,
    "rank": 101
  },
  "713447913459679304": {
    "experience": 160,
    "level": 2,
    "balance": 200,
    "rank": 73
  },
  "751882794875093083": {
    "experience": 133,
    "level": 1,
    "balance": 100,
    "rank": 112
  },
  "935992848518635570": {
    "experience": 126,
    "level": 1,
    "balance": 100,
    "rank": 123
  },
  "463376675946889237": {
    "experience": 119,
    "level": 1,
    "balance": 100,
    "rank": 252
  },
  "720775669021278268": {
    "experience": 185,
    "level": 2,
    "balance": 200,
    "rank": 52
  },
  "571591578364280833": {
    "experience": 122,
    "level": 1,
    "balance": 100,
    "rank": 204
  },
  "939464105520140328": {
    "experience": 1013,
    "level": 6,
    "balance": 600,
    "rank": 9
  },
  "754649937442111510": {
    "experience": 646,
    "level": 5,
    "balance": 500,
    "rank": 17
  },
  "536639722370629652": {
    "experience": 309,
    "level": 3,
    "balance": 300,
    "rank": 29
  },
  "738041751175954453": {
    "experience": 124,
    "level": 1,
    "balance": 100,
    "rank": 159
  },
  "389875158858334210": {
    "experience": 242,
    "level": 3,
    "balance": 300,
    "rank": 41
  },
  "793743481000165408": {
    "experience": 141,
    "level": 1,
    "balance": 100,
    "rank": 94
  },
  "521820218255867905": {
    "experience": 116,
    "level": 1,
    "balance": 100,
    "rank": 300
  },
  "413027120332406788": {
    "experience": 121,
    "level": 1,
    "balance": 100,
    "rank": 222
  },
  "322472003963584523": {
    "experience": 161,
    "level": 2,
    "balance": 200,
    "rank": 70
  },
  "297984325184651264": {
    "experience": 178,
    "level": 2,
    "balance": 200,
    "rank": 56
  },
  "519333393557618699": {
    "experience": 125,
    "level": 1,
    "balance": 100,
    "rank": 140
  },
  "681103473613209702": {
    "experience": 124,
    "level": 1,
    "balance": 100,
    "rank": 158
  },
  "753474897837293640": {
    "experience": 118,
    "level": 1,
    "balance": 100,
    "rank": 268
  },
  "708001762233155734": {
    "experience": 283,
    "level": 3,
    "balance": 300,
    "rank": 32
  },
  "833070528435585057": {
    "experience": 120,
    "level": 1,
    "balance": 100,
    "rank": 238
  },
  "557252664602132481": {
    "experience": 121,
    "level": 1,
    "balance": 100,
    "rank": 221
  },
  "681603911630716980": {
    "experience": 122,
    "level": 1,
    "balance": 100,
    "rank": 203
  },
  "579098090884038667": {
    "experience": 123,
    "level": 1,
    "balance": 100,
    "rank": 176
  },
  "383050687606685696": {
    "experience": 119,
    "level": 1,
    "balance": 100,
    "rank": 251
  },
  "274259292079783938": {
    "experience": 125,
    "level": 1,
    "balance": 100,
    "rank": 139
  },
  "741031803267317803": {
    "experience": 115,
    "level": 1,
    "balance": 100,
    "rank": 315
  },
  "302866195621871636": {
    "experience": 194,
    "level": 2,
    "balance": 200,
    "rank": 49
  },
  "871466755455852584": {
    "experience": 126,
    "level": 1,
    "balance": 100,
    "rank": 122
  },
  "294520932616372224": {
    "experience": 717,
    "level": 5,
    "balance": 500,
    "rank": 16
  },
  "355904870341148672": {
    "experience": 304,
    "level": 3,
    "balance": 300,
    "rank": 30
  },
  "640774798540144644": {
    "experience": 124,
    "level": 1,
    "balance": 100,
    "rank": 157
  },
  "504374467384836099": {
    "experience": 254,
    "level": 3,
    "balance": 300,
    "rank": 36
  },
  "802810184468135936": {
    "experience": 123,
    "level": 1,
    "balance": 100,
    "rank": 175
  },
  "941532025339412531": {
    "experience": 134,
    "level": 1,
    "balance": 100,
    "rank": 111
  },
  "250008429500825600": {
    "experience": 118,
    "level": 1,
    "balance": 100,
    "rank": 267
  },
  "599702087877525504": {
    "experience": 168,
    "level": 2,
    "balance": 200,
    "rank": 62
  },
  "516040793308528661": {
    "experience": 123,
    "level": 1,
    "balance": 100,
    "rank": 174
  },
  "656794832206823425": {
    "experience": 118,
    "level": 1,
    "balance": 100,
    "rank": 266
  },
  "545038385358831626": {
    "experience": 118,
    "level": 1,
    "balance": 100,
    "rank": 265
  },
  "577242614194110474": {
    "experience": 126,
    "level": 1,
    "balance": 100,
    "rank": 121
  },
  "783702999193223168": {
    "experience": 122,
    "level": 1,
    "balance": 100,
    "rank": 202
  },
  "388740210676203523": {
    "experience": 138,
    "level": 1,
    "balance": 100,
    "rank": 104
  },
  "298552870695862283": {
    "experience": 158,
    "level": 2,
    "balance": 200,
    "rank": 75
  },
  "698363098301726791": {
    "experience": 123,
    "level": 1,
    "balance": 100,
    "rank": 173
  },
  "159479121418649601": {
    "experience": 124,
    "level": 1,
    "balance": 100,
    "rank": 156
  },
  "401283925449900042": {
    "experience": 125,
    "level": 1,
    "balance": 100,
    "rank": 138
  },
  "731566316447858738": {
    "experience": 122,
    "level": 1,
    "balance": 100,
    "rank": 201
  },
  "610981098909990942": {
    "experience": 124,
    "level": 1,
    "balance": 100,
    "rank": 155
  },
  "482949010517262347": {
    "experience": 117,
    "level": 1,
    "balance": 100,
    "rank": 284
  },
  "291137541069864960": {
    "experience": 141,
    "level": 1,
    "balance": 100,
    "rank": 93
  },
  "727277592398266521": {
    "experience": 119,
    "level": 1,
    "balance": 100,
    "rank": 250
  },
  "443146129144807424": {
    "experience": 248,
    "level": 3,
    "balance": 300,
    "rank": 40
  },
  "719991282600116315": {
    "experience": 440,
    "level": 4,
    "balance": 400,
    "rank": 23
  },
  "621407018183294976": {
    "experience": 160,
    "level": 2,
    "balance": 200,
    "rank": 72
  },
  "760200352321896519": {
    "experience": 125,
    "level": 1,
    "balance": 100,
    "rank": 137
  },
  "762703435161403452": {
    "experience": 124,
    "level": 1,
    "balance": 100,
    "rank": 154
  },
  "927220205405499492": {
    "experience": 134,
    "level": 1,
    "balance": 100,
    "rank": 110
  },
  "610163184221028393": {
    "experience": 121,
    "level": 1,
    "balance": 100,
    "rank": 220
  },
  "324185546660511765": {
    "experience": 563,
    "level": 4,
    "balance": 400,
    "rank": 18
  },
  "934532256217825370": {
    "experience": 122,
    "level": 1,
    "balance": 100,
    "rank": 200
  },
  "462933454166687745": {
    "experience": 141,
    "level": 1,
    "balance": 100,
    "rank": 92
  },
  "509359323630010378": {
    "experience": 121,
    "level": 1,
    "balance": 100,
    "rank": 219
  },
  "836588593145184267": {
    "experience": 120,
    "level": 1,
    "balance": 100,
    "rank": 237
  },
  "665581186902392894": {
    "experience": 116,
    "level": 1,
    "balance": 100,
    "rank": 299
  },
  "625286263888674816": {
    "experience": 186,
    "level": 2,
    "balance": 200,
    "rank": 51
  },
  "539840403520749568": {
    "experience": 117,
    "level": 1,
    "balance": 100,
    "rank": 283
  },
  "350419652536696834": {
    "experience": 122,
    "level": 1,
    "balance": 100,
    "rank": 199
  },
  "316302211691053058": {
    "experience": 167,
    "level": 2,
    "balance": 200,
    "rank": 63
  },
  "195225447947042816": {
    "experience": 118,
    "level": 1,
    "balance": 100,
    "rank": 264
  },
  "449270942787436544": {
    "experience": 119,
    "level": 1,
    "balance": 100,
    "rank": 249
  },
  "369468354785837066": {
    "experience": 165,
    "level": 2,
    "balance": 200,
    "rank": 65
  },
  "804851869565714432": {
    "experience": 115,
    "level": 1,
    "balance": 100,
    "rank": 314
  },
  "604114703228338211": {
    "experience": 122,
    "level": 1,
    "balance": 100,
    "rank": 198
  },
  "654867468753567785": {
    "experience": 140,
    "level": 1,
    "balance": 100,
    "rank": 98
  },
  "389814317882540033": {
    "experience": 148,
    "level": 1,
    "balance": 100,
    "rank": 80
  },
  "226367289086312449": {
    "experience": 138,
    "level": 1,
    "balance": 100,
    "rank": 103
  },
  "173858278722371584": {
    "experience": 196,
    "level": 2,
    "balance": 200,
    "rank": 48
  },
  "445896346180911104": {
    "experience": 123,
    "level": 1,
    "balance": 100,
    "rank": 172
  },
  "840667707590574111": {
    "experience": 121,
    "level": 1,
    "balance": 100,
    "rank": 218
  },
  "442619285265973248": {
    "experience": 124,
    "level": 1,
    "balance": 100,
    "rank": 153
  },
  "610684858745749526": {
    "experience": 146,
    "level": 1,
    "balance": 100,
    "rank": 82
  },
  "934655468662587433": {
    "experience": 116,
    "level": 1,
    "balance": 100,
    "rank": 298
  },
  "675870315397513220": {
    "experience": 124,
    "level": 1,
    "balance": 100,
    "rank": 152
  },
  "931295883419586593": {
    "experience": 126,
    "level": 1,
    "balance": 100,
    "rank": 120
  },
  "721388967710294088": {
    "experience": 121,
    "level": 1,
    "balance": 100,
    "rank": 217
  },
  "761304356569088050": {
    "experience": 121,
    "level": 1,
    "balance": 100,
    "rank": 216
  },
  "275645192445493248": {
    "experience": 174,
    "level": 2,
    "balance": 200,
    "rank": 59
  },
  "310404680012398593": {
    "experience": 121,
    "level": 1,
    "balance": 100,
    "rank": 215
  },
  "196782411084857345": {
    "experience": 120,
    "level": 1,
    "balance": 100,
    "rank": 236
  },
  "511452222043848704": {
    "experience": 717,
    "level": 5,
    "balance": 500,
    "rank": 15
  },
  "585938597044289536": {
    "experience": 122,
    "level": 1,
    "balance": 100,
    "rank": 197
  },
  "693077617011589182": {
    "experience": 409,
    "level": 4,
    "balance": 400,
    "rank": 25
  },
  "578344208025255937": {
    "experience": 121,
    "level": 1,
    "balance": 100,
    "rank": 214
  },
  "179761880359895042": {
    "experience": 121,
    "level": 1,
    "balance": 100,
    "rank": 213
  },
  "748432567589535835": {
    "experience": 338,
    "level": 3,
    "balance": 300,
    "rank": 27
  },
  "389537856202211328": {
    "experience": 115,
    "level": 1,
    "balance": 100,
    "rank": 313
  },
  "730122634322378884": {
    "experience": 122,
    "level": 1,
    "balance": 100,
    "rank": 196
  },
  "653319795282018366": {
    "experience": 135,
    "level": 1,
    "balance": 100,
    "rank": 109
  },
  "714577789910646916": {
    "experience": 123,
    "level": 1,
    "balance": 100,
    "rank": 171
  },
  "621458200218173498": {
    "experience": 115,
    "level": 1,
    "balance": 100,
    "rank": 312
  },
  "391337694736678912": {
    "experience": 117,
    "level": 1,
    "balance": 100,
    "rank": 282
  },
  "928811486749552640": {
    "experience": 119,
    "level": 1,
    "balance": 100,
    "rank": 248
  },
  "194595356154134529": {
    "experience": 124,
    "level": 1,
    "balance": 100,
    "rank": 151
  },
  "540599189248278534": {
    "experience": 145,
    "level": 1,
    "balance": 100,
    "rank": 85
  },
  "932706520850894858": {
    "experience": 121,
    "level": 1,
    "balance": 100,
    "rank": 212
  },
  "363748917399126016": {
    "experience": 131,
    "level": 1,
    "balance": 100,
    "rank": 113
  },
  "910110430339416065": {
    "experience": 115,
    "level": 1,
    "balance": 100,
    "rank": 311
  },
  "659666163013255168": {
    "experience": 118,
    "level": 1,
    "balance": 100,
    "rank": 263
  },
  "837549092208115712": {
    "experience": 123,
    "level": 1,
    "balance": 100,
    "rank": 170
  },
  "788815140468031569": {
    "experience": 169,
    "level": 2,
    "balance": 200,
    "rank": 61
  },
  "746544048323428442": {
    "experience": 126,
    "level": 1,
    "balance": 100,
    "rank": 119
  },
  "945342150520999937": {
    "experience": 126,
    "level": 1,
    "balance": 100,
    "rank": 118
  },
  "576428316459008009": {
    "experience": 160,
    "level": 2,
    "balance": 200,
    "rank": 71
  },
  "780869102729822210": {
    "experience": 125,
    "level": 1,
    "balance": 100,
    "rank": 136
  },
  "578730674572361737": {
    "experience": 148,
    "level": 1,
    "balance": 100,
    "rank": 79
  },
  "850510768096149525": {
    "experience": 120,
    "level": 1,
    "balance": 100,
    "rank": 235
  },
  "768931498719576074": {
    "experience": 123,
    "level": 1,
    "balance": 100,
    "rank": 169
  },
  "668492748902498304": {
    "experience": 115,
    "level": 1,
    "balance": 100,
    "rank": 310
  },
  "652739685109727232": {
    "experience": 139,
    "level": 1,
    "balance": 100,
    "rank": 100
  },
  "753027405970538607": {
    "experience": 100,
    "level": 1,
    "balance": 100,
    "rank": 320
  },
  "333415462182584320": {
    "experience": 137,
    "level": 1,
    "balance": 100,
    "rank": 107
  },
  "402651390444306433": {
    "experience": 394,
    "level": 4,
    "balance": 400,
    "rank": 26
  },
  "918211065844732004": {
    "experience": 119,
    "level": 1,
    "balance": 100,
    "rank": 247
  },
  "833751756881002527": {
    "experience": 121,
    "level": 1,
    "balance": 100,
    "rank": 211
  },
  "529753984726990848": {
    "experience": 141,
    "level": 1,
    "balance": 100,
    "rank": 91
  },
  "826907740035219487": {
    "experience": 116,
    "level": 1,
    "balance": 100,
    "rank": 297
  },
  "261608603725725697": {
    "experience": 193,
    "level": 2,
    "balance": 200,
    "rank": 50
  },
  "874122695049109564": {
    "experience": 116,
    "level": 1,
    "balance": 100,
    "rank": 296
  },
  "772319725350027305": {
    "experience": 116,
    "level": 1,
    "balance": 100,
    "rank": 295
  },
  "440105408837844992": {
    "experience": 181,
    "level": 2,
    "balance": 200,
    "rank": 53
  },
  "709049282333900901": {
    "experience": 125,
    "level": 1,
    "balance": 100,
    "rank": 135
  },
  "938690709471518731": {
    "experience": 115,
    "level": 1,
    "balance": 100,
    "rank": 309
  },
  "788566521638682654": {
    "experience": 116,
    "level": 1,
    "balance": 100,
    "rank": 294
  },
  "896207647685107753": {
    "experience": 122,
    "level": 1,
    "balance": 100,
    "rank": 195
  },
  "596902190334083073": {
    "experience": 140,
    "level": 1,
    "balance": 100,
    "rank": 97
  },
  "856982503223197736": {
    "experience": 117,
    "level": 1,
    "balance": 100,
    "rank": 281
  },
  "169533674906320896": {
    "experience": 115,
    "level": 1,
    "balance": 100,
    "rank": 308
  },
  "650199857885347860": {
    "experience": 140,
    "level": 1,
    "balance": 100,
    "rank": 96
  },
  "200774083107880960": {
    "experience": 302,
    "level": 3,
    "balance": 300,
    "rank": 31
  },
  "441746798441136128": {
    "experience": 166,
    "level": 2,
    "balance": 200,
    "rank": 64
  },
  "424964819242975253": {
    "experience": 100,
    "level": 1,
    "balance": 100,
    "rank": 319
  },
  "346083484504293398": {
    "experience": 118,
    "level": 1,
    "balance": 100,
    "rank": 262
  },
  "754875264168624219": {
    "experience": 116,
    "level": 1,
    "balance": 100,
    "rank": 293
  },
  "294364370622742529": {
    "experience": 123,
    "level": 1,
    "balance": 100,
    "rank": 168
  },
  "751609658048905256": {
    "experience": 125,
    "level": 1,
    "balance": 100,
    "rank": 134
  },
  "625347160283807756": {
    "experience": 124,
    "level": 1,
    "balance": 100,
    "rank": 150
  },
  "952707903704403989": {
    "experience": 122,
    "level": 1,
    "balance": 100,
    "rank": 194
  },
  "266548772518100992": {
    "experience": 120,
    "level": 1,
    "balance": 100,
    "rank": 234
  },
  "788491090645876756": {
    "experience": 117,
    "level": 1,
    "balance": 100,
    "rank": 280
  },
  "677394927591882762": {
    "experience": 161,
    "level": 2,
    "balance": 200,
    "rank": 69
  },
  "900209392228651008": {
    "experience": 117,
    "level": 1,
    "balance": 100,
    "rank": 279
  },
  "496580035944382474": {
    "experience": 125,
    "level": 1,
    "balance": 100,
    "rank": 133
  },
  "619733962180263995": {
    "experience": 135,
    "level": 1,
    "balance": 100,
    "rank": 108
  },
  "883725314449109082": {
    "experience": 470,
    "level": 4,
    "balance": 400,
    "rank": 22
  },
  "857696678563151942": {
    "experience": 2901,
    "level": 8,
    "balance": 1100,
    "rank": 7
  },
  "428997969442897920": {
    "experience": 116,
    "level": 1,
    "balance": 100,
    "rank": 292
  },
  "339981505860468736": {
    "experience": 120,
    "level": 1,
    "balance": 100,
    "rank": 233
  },
  "474291296148652042": {
    "experience": 155,
    "level": 2,
    "balance": 200,
    "rank": 78
  },
  "873214263722922044": {
    "experience": 119,
    "level": 1,
    "balance": 100,
    "rank": 246
  },
  "318153717767471104": {
    "experience": 119,
    "level": 1,
    "balance": 100,
    "rank": 245
  },
  "845004788625571900": {
    "experience": 120,
    "level": 1,
    "balance": 100,
    "rank": 232
  },
  "417727911215235074": {
    "experience": 157,
    "level": 2,
    "balance": 200,
    "rank": 76
  },
  "328711838076502018": {
    "experience": 272,
    "level": 3,
    "balance": 300,
    "rank": 35
  },
  "430850636158861315": {
    "experience": 215,
    "level": 2,
    "balance": 200,
    "rank": 46
  },
  "512066768504619026": {
    "experience": 119,
    "level": 1,
    "balance": 100,
    "rank": 244
  },
  "691743504577200188": {
    "experience": 121,
    "level": 1,
    "balance": 100,
    "rank": 210
  },
  "744616808212070492": {
    "experience": 125,
    "level": 1,
    "balance": 100,
    "rank": 132
  },
  "486228581521817620": {
    "experience": 122,
    "level": 1,
    "balance": 100,
    "rank": 193
  },
  "463965279861473280": {
    "experience": 115,
    "level": 1,
    "balance": 100,
    "rank": 307
  },
  "482170635683102723": {
    "experience": 117,
    "level": 1,
    "balance": 100,
    "rank": 278
  },
  "540241258669408288": {
    "experience": 125,
    "level": 1,
    "balance": 100,
    "rank": 131
  },
  "522145407887867904": {
    "experience": 230,
    "level": 2,
    "balance": 200,
    "rank": 43
  },
  "343981184730267659": {
    "experience": 116,
    "level": 1,
    "balance": 100,
    "rank": 291
  },
  "322837005438287874": {
    "experience": 419,
    "level": 4,
    "balance": 400,
    "rank": 24
  },
  "745675086966816828": {
    "experience": 225,
    "level": 2,
    "balance": 200,
    "rank": 44
  },
  "279347754378199040": {
    "experience": 116,
    "level": 1,
    "balance": 100,
    "rank": 290
  },
  "767483577117179953": {
    "experience": 140,
    "level": 1,
    "balance": 100,
    "rank": 95
  },
  "720387843536584746": {
    "experience": 124,
    "level": 1,
    "balance": 100,
    "rank": 149
  },
  "533537865171468288": {
    "experience": 124,
    "level": 1,
    "balance": 100,
    "rank": 148
  },
  "400042115075145729": {
    "experience": 121,
    "level": 1,
    "balance": 100,
    "rank": 209
  },
  "217756379996356611": {
    "experience": 115,
    "level": 1,
    "balance": 100,
    "rank": 306
  },
  "490325287813382150": {
    "experience": 224,
    "level": 2,
    "balance": 200,
    "rank": 45
  },
  "520797847554097162": {
    "experience": 122,
    "level": 1,
    "balance": 100,
    "rank": 192
  },
  "485649857378254859": {
    "experience": 178,
    "level": 2,
    "balance": 200,
    "rank": 55
  },
  "769515081678979074": {
    "experience": 120,
    "level": 1,
    "balance": 100,
    "rank": 231
  },
  "866413585001480203": {
    "experience": 117,
    "level": 1,
    "balance": 100,
    "rank": 277
  },
  "327235387527528450": {
    "experience": 115,
    "level": 1,
    "balance": 100,
    "rank": 305
  },
  "693844752826630204": {
    "experience": 120,
    "level": 1,
    "balance": 100,
    "rank": 230
  },
  "948043037265756191": {
    "experience": 124,
    "level": 1,
    "balance": 100,
    "rank": 147
  },
  "722551071192383608": {
    "experience": 176,
    "level": 2,
    "balance": 200,
    "rank": 58
  },
  "923754687201681458": {
    "experience": 125,
    "level": 1,
    "balance": 100,
    "rank": 130
  },
  "699457312514900050": {
    "experience": 141,
    "level": 1,
    "balance": 100,
    "rank": 90
  },
  "692827665643733072": {
    "experience": 122,
    "level": 1,
    "balance": 100,
    "rank": 191
  },
  "547840353860976680": {
    "experience": 117,
    "level": 1,
    "balance": 100,
    "rank": 276
  },
  "708225756647522326": {
    "experience": 100,
    "level": 1,
    "balance": 100,
    "rank": 318
  },
  "310530613994192907": {
    "experience": 122,
    "level": 1,
    "balance": 100,
    "rank": 190
  },
  "407051486535614474": {
    "experience": 162,
    "level": 2,
    "balance": 200,
    "rank": 68
  },
  "310957416080736257": {
    "experience": 117,
    "level": 1,
    "balance": 100,
    "rank": 275
  },
  "933771616645701693": {
    "experience": 124,
    "level": 1,
    "balance": 100,
    "rank": 146
  },
  "765368658720456704": {
    "experience": 124,
    "level": 1,
    "balance": 100,
    "rank": 145
  },
  "769779447641145424": {
    "experience": 119,
    "level": 1,
    "balance": 100,
    "rank": 243
  },
  "872294948815384626": {
    "experience": 120,
    "level": 1,
    "balance": 100,
    "rank": 229
  },
  "764681893026332694": {
    "experience": 121,
    "level": 1,
    "balance": 100,
    "rank": 208
  },
  "659190748734029844": {
    "experience": 120,
    "level": 1,
    "balance": 100,
    "rank": 228
  },
  "769568749870120960": {
    "experience": 156,
    "level": 2,
    "balance": 200,
    "rank": 77
  },
  "297376436786823168": {
    "experience": 117,
    "level": 1,
    "balance": 100,
    "rank": 274
  },
  "687378513472258153": {
    "experience": 116,
    "level": 1,
    "balance": 100,
    "rank": 289
  },
  "955851811141599314": {
    "experience": 145,
    "level": 1,
    "balance": 100,
    "rank": 84
  },
  "955875431867895818": {
    "experience": 123,
    "level": 1,
    "balance": 100,
    "rank": 167
  },
  "842817689789136907": {
    "experience": 119,
    "level": 1,
    "balance": 100,
    "rank": 242
  },
  "400520274652430347": {
    "experience": 142,
    "level": 1,
    "balance": 100,
    "rank": 88
  },
  "798790603189256212": {
    "experience": 120,
    "level": 1,
    "balance": 100,
    "rank": 227
  },
  "804167707477934120": {
    "experience": 117,
    "level": 1,
    "balance": 100,
    "rank": 273
  },
  "203626861631111168": {
    "experience": 123,
    "level": 1,
    "balance": 100,
    "rank": 166
  },
  "955970851285639189": {
    "experience": 118,
    "level": 1,
    "balance": 100,
    "rank": 261
  },
  "701535757327663104": {
    "experience": 124,
    "level": 1,
    "balance": 100,
    "rank": 144
  },
  "387389893359173635": {
    "experience": 164,
    "level": 2,
    "balance": 200,
    "rank": 66
  },
  "189476451765059595": {
    "experience": 115,
    "level": 1,
    "balance": 100,
    "rank": 304
  },
  "356509775955230722": {
    "experience": 122,
    "level": 1,
    "balance": 100,
    "rank": 189
  },
  "798670758087098389": {
    "experience": 118,
    "level": 1,
    "balance": 100,
    "rank": 260
  },
  "524857654368141323": {
    "experience": 278,
    "level": 3,
    "balance": 300,
    "rank": 34
  },
  "869362646695153684": {
    "experience": 145,
    "level": 1,
    "balance": 100,
    "rank": 83
  },
  "849081717326086174": {
    "experience": 126,
    "level": 1,
    "balance": 100,
    "rank": 117
  },
  "901322605963923486": {
    "experience": 144,
    "level": 1,
    "balance": 100,
    "rank": 86
  },
  "830900894828199956": {
    "experience": 123,
    "level": 1,
    "balance": 100,
    "rank": 165
  },
  "536804312567906305": {
    "experience": 125,
    "level": 1,
    "balance": 100,
    "rank": 129
  },
  "788938122481369088": {
    "experience": 115,
    "level": 1,
    "balance": 100,
    "rank": 303
  },
  "716086415577841706": {
    "experience": 117,
    "level": 1,
    "balance": 100,
    "rank": 272
  },
  "935784546245410837": {
    "experience": 116,
    "level": 1,
    "balance": 100,
    "rank": 288
  },
  "137230103812898816": {
    "experience": 120,
    "level": 1,
    "balance": 100,
    "rank": 226
  },
  "767191669589803099": {
    "experience": 313,
    "level": 3,
    "balance": 300,
    "rank": 28
  },
  "728005818162741308": {
    "experience": 121,
    "level": 1,
    "balance": 100,
    "rank": 207
  },
  "826820380307357777": {
    "experience": 122,
    "level": 1,
    "balance": 100,
    "rank": 188
  },
  "956200379572445224": {
    "experience": 123,
    "level": 1,
    "balance": 100,
    "rank": 164
  },
  "728312232093679657": {
    "experience": 118,
    "level": 1,
    "balance": 100,
    "rank": 259
  },
  "877612715353456720": {
    "experience": 121,
    "level": 1,
    "balance": 100,
    "rank": 206
  },
  "201880526049509377": {
    "experience": 124,
    "level": 1,
    "balance": 100,
    "rank": 143
  },
  "925365372654325801": {
    "experience": 118,
    "level": 1,
    "balance": 100,
    "rank": 258
  },
  "404071178441981975": {
    "experience": 125,
    "level": 1,
    "balance": 100,
    "rank": 128
  },
  "551189606423461898": {
    "experience": 123,
    "level": 1,
    "balance": 100,
    "rank": 163
  },
  "693161762920595558": {
    "experience": 119,
    "level": 1,
    "balance": 100,
    "rank": 241
  },
  "216941997792034817": {
    "experience": 120,
    "level": 1,
    "balance": 100,
    "rank": 225
  },
  "956334460067008552": {
    "experience": 235,
    "level": 2,
    "balance": 200,
    "rank": 42
  },
  "730887743361777685": {
    "experience": 137,
    "level": 1,
    "balance": 100,
    "rank": 106
  },
  "505587072254607361": {
    "experience": 180,
    "level": 2,
    "balance": 200,
    "rank": 54
  },
  "693917242403848282": {
    "experience": 137,
    "level": 1,
    "balance": 100,
    "rank": 105
  },
  "845041119141822585": {
    "experience": 126,
    "level": 1,
    "balance": 100,
    "rank": 116
  },
  "733413373219307641": {
    "experience": 117,
    "level": 1,
    "balance": 100,
    "rank": 271
  },
  "956507726631022602": {
    "experience": 123,
    "level": 1,
    "balance": 100,
    "rank": 162
  },
  "853299845863571473": {
    "experience": 122,
    "level": 1,
    "balance": 100,
    "rank": 187
  },
  "956555102213255188": {
    "experience": 126,
    "level": 1,
    "balance": 100,
    "rank": 115
  },
  "689428958504026113": {
    "experience": 100,
    "level": 1,
    "balance": 100,
    "rank": 317
  },
  "226132892613476354": {
    "experience": 126,
    "level": 1,
    "balance": 100,
    "rank": 114
  },
  "550058626643918848": {
    "experience": 122,
    "level": 1,
    "balance": 100,
    "rank": 186
  },
  "673327239575765069": {
    "experience": 176,
    "level": 2,
    "balance": 200,
    "rank": 57
  },
  "634641433961168906": {
    "experience": 119,
    "level": 1,
    "balance": 100,
    "rank": 240
  },
  "537814868707770369": {
    "experience": 158,
    "level": 2,
    "balance": 200,
    "rank": 74
  },
  "776362717014523904": {
    "experience": 120,
    "level": 1,
    "balance": 100,
    "rank": 224
  },
  "659857350936494121": {
    "experience": 139,
    "level": 1,
    "balance": 100,
    "rank": 99
  },
  "725034610479726594": {
    "experience": 124,
    "level": 1,
    "balance": 100,
    "rank": 142
  },
  "453283328011796501": {
    "experience": 125,
    "level": 1,
    "balance": 100,
    "rank": 127
  },
  "900067824188424232": {
    "experience": 125,
    "level": 1,
    "balance": 100,
    "rank": 126
  },
  "750024233169715290": {
    "experience": 123,
    "level": 1,
    "balance": 100,
    "rank": 161
  },
  "929465000735678595": {
    "experience": 125,
    "level": 1,
    "balance": 100,
    "rank": 125
  },
  "937822572706414634": {
    "experience": 122,
    "level": 1,
    "balance": 100,
    "rank": 185
  },
  "950127147794702356": {
    "experience": 125,
    "level": 1,
    "balance": 100,
    "rank": 124
  },
  "949086584857309255": {
    "experience": 146,
    "level": 1,
    "balance": 100,
    "rank": 81
  },
  "441779536544268294": {
    "experience": 173,
    "level": 2,
    "balance": 200,
    "rank": 60
  },
  "723621159626735738": {
    "experience": 122,
    "level": 1,
    "balance": 100,
    "rank": 184
  },
  "925944990125932544": {
    "experience": 124,
    "level": 1,
    "balance": 100,
    "rank": 141
  }
}